{
  "directed": false,
  "multigraph": false,
  "graph": {},
  "nodes": [
    {
      "label": "next.config.ts",
      "file_type": "code",
      "source_file": "next.config.ts",
      "source_location": "L1",
      "id": "next_config_ts",
      "community": 20,
      "norm_label": "next.config.ts"
    },
    {
      "label": "postcss.config.mjs",
      "file_type": "code",
      "source_file": "postcss.config.mjs",
      "source_location": "L1",
      "id": "postcss_config_mjs",
      "community": 21,
      "norm_label": "postcss.config.mjs"
    },
    {
      "label": "next-env.d.ts",
      "file_type": "code",
      "source_file": "next-env.d.ts",
      "source_location": "L1",
      "id": "next_env_d_ts",
      "community": 22,
      "norm_label": "next-env.d.ts"
    },
    {
      "label": "useStore.ts",
      "file_type": "code",
      "source_file": "src/lib/store/useStore.ts",
      "source_location": "L1",
      "id": "src_lib_store_usestore_ts",
      "community": 23,
      "norm_label": "usestore.ts"
    },
    {
      "label": "useGoogleOAuth.ts",
      "file_type": "code",
      "source_file": "src/lib/hooks/useGoogleOAuth.ts",
      "source_location": "L1",
      "id": "src_lib_hooks_usegoogleoauth_ts",
      "community": 8,
      "norm_label": "usegoogleoauth.ts"
    },
    {
      "label": "loadGoogleSDK()",
      "file_type": "code",
      "source_file": "src/lib/hooks/useGoogleOAuth.ts",
      "source_location": "L19",
      "id": "hooks_usegoogleoauth_loadgooglesdk",
      "community": 8,
      "norm_label": "loadgooglesdk()"
    },
    {
      "label": "useGoogleOAuth()",
      "file_type": "code",
      "source_file": "src/lib/hooks/useGoogleOAuth.ts",
      "source_location": "L32",
      "id": "hooks_usegoogleoauth_usegoogleoauth",
      "community": 8,
      "norm_label": "usegoogleoauth()"
    },
    {
      "label": "sheets.ts",
      "file_type": "code",
      "source_file": "src/lib/google/sheets.ts",
      "source_location": "L1",
      "id": "src_lib_google_sheets_ts",
      "community": 1,
      "norm_label": "sheets.ts"
    },
    {
      "label": "sectionDataEnd()",
      "file_type": "code",
      "source_file": "src/lib/google/sheets.ts",
      "source_location": "L29",
      "id": "google_sheets_sectiondataend",
      "community": 0,
      "norm_label": "sectiondataend()"
    },
    {
      "label": "quoteSheet()",
      "file_type": "code",
      "source_file": "src/lib/google/sheets.ts",
      "source_location": "L39",
      "id": "google_sheets_quotesheet",
      "community": 1,
      "norm_label": "quotesheet()"
    },
    {
      "label": "getMonthLabel()",
      "file_type": "code",
      "source_file": "src/lib/google/sheets.ts",
      "source_location": "L43",
      "id": "google_sheets_getmonthlabel",
      "community": 1,
      "norm_label": "getmonthlabel()"
    },
    {
      "label": "monthLabelToNum()",
      "file_type": "code",
      "source_file": "src/lib/google/sheets.ts",
      "source_location": "L50",
      "id": "google_sheets_monthlabeltonum",
      "community": 1,
      "norm_label": "monthlabeltonum()"
    },
    {
      "label": "currentMonthLabel()",
      "file_type": "code",
      "source_file": "src/lib/google/sheets.ts",
      "source_location": "L55",
      "id": "google_sheets_currentmonthlabel",
      "community": 1,
      "norm_label": "currentmonthlabel()"
    },
    {
      "label": "SheetsService",
      "file_type": "code",
      "source_file": "src/lib/google/sheets.ts",
      "source_location": "L60",
      "id": "google_sheets_sheetsservice",
      "community": 0,
      "norm_label": "sheetsservice"
    },
    {
      "label": ".constructor()",
      "file_type": "code",
      "source_file": "src/lib/google/sheets.ts",
      "source_location": "L64",
      "id": "google_sheets_sheetsservice_constructor",
      "community": 0,
      "norm_label": ".constructor()"
    },
    {
      "label": ".listSheets()",
      "file_type": "code",
      "source_file": "src/lib/google/sheets.ts",
      "source_location": "L69",
      "id": "google_sheets_sheetsservice_listsheets",
      "community": 0,
      "norm_label": ".listsheets()"
    },
    {
      "label": ".createBudgetSheet()",
      "file_type": "code",
      "source_file": "src/lib/google/sheets.ts",
      "source_location": "L92",
      "id": "google_sheets_sheetsservice_createbudgetsheet",
      "community": 0,
      "norm_label": ".createbudgetsheet()"
    },
    {
      "label": ".validateSheet()",
      "file_type": "code",
      "source_file": "src/lib/google/sheets.ts",
      "source_location": "L155",
      "id": "google_sheets_sheetsservice_validatesheet",
      "community": 0,
      "norm_label": ".validatesheet()"
    },
    {
      "label": ".getSheetDetails()",
      "file_type": "code",
      "source_file": "src/lib/google/sheets.ts",
      "source_location": "L174",
      "id": "google_sheets_sheetsservice_getsheetdetails",
      "community": 0,
      "norm_label": ".getsheetdetails()"
    },
    {
      "label": ".getConfigSheetNumericId()",
      "file_type": "code",
      "source_file": "src/lib/google/sheets.ts",
      "source_location": "L190",
      "id": "google_sheets_sheetsservice_getconfigsheetnumericid",
      "community": 0,
      "norm_label": ".getconfigsheetnumericid()"
    },
    {
      "label": ".readConfig()",
      "file_type": "code",
      "source_file": "src/lib/google/sheets.ts",
      "source_location": "L195",
      "id": "google_sheets_sheetsservice_readconfig",
      "community": 1,
      "norm_label": ".readconfig()"
    },
    {
      "label": ".addConfigItem()",
      "file_type": "code",
      "source_file": "src/lib/google/sheets.ts",
      "source_location": "L291",
      "id": "google_sheets_sheetsservice_addconfigitem",
      "community": 0,
      "norm_label": ".addconfigitem()"
    },
    {
      "label": ".updateConfigItem()",
      "file_type": "code",
      "source_file": "src/lib/google/sheets.ts",
      "source_location": "L362",
      "id": "google_sheets_sheetsservice_updateconfigitem",
      "community": 0,
      "norm_label": ".updateconfigitem()"
    },
    {
      "label": ".deleteConfigItem()",
      "file_type": "code",
      "source_file": "src/lib/google/sheets.ts",
      "source_location": "L391",
      "id": "google_sheets_sheetsservice_deleteconfigitem",
      "community": 0,
      "norm_label": ".deleteconfigitem()"
    },
    {
      "label": ".syncFixedExpensesToAllMonthSheets()",
      "file_type": "code",
      "source_file": "src/lib/google/sheets.ts",
      "source_location": "L422",
      "id": "google_sheets_sheetsservice_syncfixedexpensestoallmonthsheets",
      "community": 1,
      "norm_label": ".syncfixedexpensestoallmonthsheets()"
    },
    {
      "label": ".syncFixedExpensesToMonthSheet()",
      "file_type": "code",
      "source_file": "src/lib/google/sheets.ts",
      "source_location": "L446",
      "id": "google_sheets_sheetsservice_syncfixedexpensestomonthsheet",
      "community": 1,
      "norm_label": ".syncfixedexpensestomonthsheet()"
    },
    {
      "label": ".createMonthSheet()",
      "file_type": "code",
      "source_file": "src/lib/google/sheets.ts",
      "source_location": "L514",
      "id": "google_sheets_sheetsservice_createmonthsheet",
      "community": 1,
      "norm_label": ".createmonthsheet()"
    },
    {
      "label": ".readTransactions()",
      "file_type": "code",
      "source_file": "src/lib/google/sheets.ts",
      "source_location": "L583",
      "id": "google_sheets_sheetsservice_readtransactions",
      "community": 1,
      "norm_label": ".readtransactions()"
    },
    {
      "label": ".setManyMonthlyIncomeOverrides()",
      "file_type": "code",
      "source_file": "src/lib/google/sheets.ts",
      "source_location": "L642",
      "id": "google_sheets_sheetsservice_setmanymonthlyincomeoverrides",
      "community": 0,
      "norm_label": ".setmanymonthlyincomeoverrides()"
    },
    {
      "label": ".setManyFixedExpenseOverrides()",
      "file_type": "code",
      "source_file": "src/lib/google/sheets.ts",
      "source_location": "L677",
      "id": "google_sheets_sheetsservice_setmanyfixedexpenseoverrides",
      "community": 0,
      "norm_label": ".setmanyfixedexpenseoverrides()"
    },
    {
      "label": ".setMonthlyIncomeOverride()",
      "file_type": "code",
      "source_file": "src/lib/google/sheets.ts",
      "source_location": "L713",
      "id": "google_sheets_sheetsservice_setmonthlyincomeoverride",
      "community": 0,
      "norm_label": ".setmonthlyincomeoverride()"
    },
    {
      "label": ".deleteMonthlyIncomeOverride()",
      "file_type": "code",
      "source_file": "src/lib/google/sheets.ts",
      "source_location": "L768",
      "id": "google_sheets_sheetsservice_deletemonthlyincomeoverride",
      "community": 0,
      "norm_label": ".deletemonthlyincomeoverride()"
    },
    {
      "label": ".setFixedExpenseOverride()",
      "file_type": "code",
      "source_file": "src/lib/google/sheets.ts",
      "source_location": "L793",
      "id": "google_sheets_sheetsservice_setfixedexpenseoverride",
      "community": 0,
      "norm_label": ".setfixedexpenseoverride()"
    },
    {
      "label": ".deleteFixedExpenseOverride()",
      "file_type": "code",
      "source_file": "src/lib/google/sheets.ts",
      "source_location": "L849",
      "id": "google_sheets_sheetsservice_deletefixedexpenseoverride",
      "community": 0,
      "norm_label": ".deletefixedexpenseoverride()"
    },
    {
      "label": ".addTransaction()",
      "file_type": "code",
      "source_file": "src/lib/google/sheets.ts",
      "source_location": "L875",
      "id": "google_sheets_sheetsservice_addtransaction",
      "community": 1,
      "norm_label": ".addtransaction()"
    },
    {
      "label": ".deleteTransaction()",
      "file_type": "code",
      "source_file": "src/lib/google/sheets.ts",
      "source_location": "L914",
      "id": "google_sheets_sheetsservice_deletetransaction",
      "community": 0,
      "norm_label": ".deletetransaction()"
    },
    {
      "label": "layout.tsx",
      "file_type": "code",
      "source_file": "src/app/layout.tsx",
      "source_location": "L1",
      "id": "src_app_layout_tsx",
      "community": 10,
      "norm_label": "layout.tsx"
    },
    {
      "label": "RootLayout()",
      "file_type": "code",
      "source_file": "src/app/layout.tsx",
      "source_location": "L21",
      "id": "app_layout_rootlayout",
      "community": 10,
      "norm_label": "rootlayout()"
    },
    {
      "label": "page.tsx",
      "file_type": "code",
      "source_file": "src/app/page.tsx",
      "source_location": "L1",
      "id": "src_app_page_tsx",
      "community": 9,
      "norm_label": "page.tsx"
    },
    {
      "label": "GoogleG()",
      "file_type": "code",
      "source_file": "src/app/page.tsx",
      "source_location": "L8",
      "id": "app_page_googleg",
      "community": 9,
      "norm_label": "googleg()"
    },
    {
      "label": "handleLogin()",
      "file_type": "code",
      "source_file": "src/app/page.tsx",
      "source_location": "L30",
      "id": "app_page_handlelogin",
      "community": 9,
      "norm_label": "handlelogin()"
    },
    {
      "label": "page.tsx",
      "file_type": "code",
      "source_file": "src/app/sheets/select/page.tsx",
      "source_location": "L1",
      "id": "src_app_sheets_select_page_tsx",
      "community": 7,
      "norm_label": "page.tsx"
    },
    {
      "label": "onDown()",
      "file_type": "code",
      "source_file": "src/app/sheets/select/page.tsx",
      "source_location": "L21",
      "id": "select_page_ondown",
      "community": 7,
      "norm_label": "ondown()"
    },
    {
      "label": "handleSelectSheet()",
      "file_type": "code",
      "source_file": "src/app/sheets/select/page.tsx",
      "source_location": "L42",
      "id": "select_page_handleselectsheet",
      "community": 7,
      "norm_label": "handleselectsheet()"
    },
    {
      "label": "handleCreateNew()",
      "file_type": "code",
      "source_file": "src/app/sheets/select/page.tsx",
      "source_location": "L69",
      "id": "select_page_handlecreatenew",
      "community": 7,
      "norm_label": "handlecreatenew()"
    },
    {
      "label": "page.tsx",
      "file_type": "code",
      "source_file": "src/app/dashboard/page.tsx",
      "source_location": "L1",
      "id": "src_app_dashboard_page_tsx",
      "community": 2,
      "norm_label": "page.tsx"
    },
    {
      "label": "onDown()",
      "file_type": "code",
      "source_file": "src/app/dashboard/page.tsx",
      "source_location": "L42",
      "id": "dashboard_page_ondown",
      "community": 2,
      "norm_label": "ondown()"
    },
    {
      "label": "getPastMonthKeys()",
      "file_type": "code",
      "source_file": "src/app/dashboard/page.tsx",
      "source_location": "L143",
      "id": "dashboard_page_getpastmonthkeys",
      "community": 2,
      "norm_label": "getpastmonthkeys()"
    },
    {
      "label": "handleConfigAdd()",
      "file_type": "code",
      "source_file": "src/app/dashboard/page.tsx",
      "source_location": "L149",
      "id": "dashboard_page_handleconfigadd",
      "community": 2,
      "norm_label": "handleconfigadd()"
    },
    {
      "label": "handleConfigEdit()",
      "file_type": "code",
      "source_file": "src/app/dashboard/page.tsx",
      "source_location": "L164",
      "id": "dashboard_page_handleconfigedit",
      "community": 2,
      "norm_label": "handleconfigedit()"
    },
    {
      "label": "handleConfigDelete()",
      "file_type": "code",
      "source_file": "src/app/dashboard/page.tsx",
      "source_location": "L179",
      "id": "dashboard_page_handleconfigdelete",
      "community": 2,
      "norm_label": "handleconfigdelete()"
    },
    {
      "label": "handleSetIncome()",
      "file_type": "code",
      "source_file": "src/app/dashboard/page.tsx",
      "source_location": "L193",
      "id": "dashboard_page_handlesetincome",
      "community": 2,
      "norm_label": "handlesetincome()"
    },
    {
      "label": "handleSetMonthlyIncomeOverride()",
      "file_type": "code",
      "source_file": "src/app/dashboard/page.tsx",
      "source_location": "L204",
      "id": "dashboard_page_handlesetmonthlyincomeoverride",
      "community": 2,
      "norm_label": "handlesetmonthlyincomeoverride()"
    },
    {
      "label": "handleDeleteMonthlyIncomeOverride()",
      "file_type": "code",
      "source_file": "src/app/dashboard/page.tsx",
      "source_location": "L220",
      "id": "dashboard_page_handledeletemonthlyincomeoverride",
      "community": 2,
      "norm_label": "handledeletemonthlyincomeoverride()"
    },
    {
      "label": "handleSetFixedExpenseOverride()",
      "file_type": "code",
      "source_file": "src/app/dashboard/page.tsx",
      "source_location": "L233",
      "id": "dashboard_page_handlesetfixedexpenseoverride",
      "community": 2,
      "norm_label": "handlesetfixedexpenseoverride()"
    },
    {
      "label": "handleDeleteFixedExpenseOverride()",
      "file_type": "code",
      "source_file": "src/app/dashboard/page.tsx",
      "source_location": "L250",
      "id": "dashboard_page_handledeletefixedexpenseoverride",
      "community": 2,
      "norm_label": "handledeletefixedexpenseoverride()"
    },
    {
      "label": "handleAddTransaction()",
      "file_type": "code",
      "source_file": "src/app/dashboard/page.tsx",
      "source_location": "L267",
      "id": "dashboard_page_handleaddtransaction",
      "community": 2,
      "norm_label": "handleaddtransaction()"
    },
    {
      "label": "handleDeleteTransaction()",
      "file_type": "code",
      "source_file": "src/app/dashboard/page.tsx",
      "source_location": "L336",
      "id": "dashboard_page_handledeletetransaction",
      "community": 2,
      "norm_label": "handledeletetransaction()"
    },
    {
      "label": "route.ts",
      "file_type": "code",
      "source_file": "src/app/api/transactions/route.ts",
      "source_location": "L1",
      "id": "src_app_api_transactions_route_ts",
      "community": 11,
      "norm_label": "route.ts"
    },
    {
      "label": "GET()",
      "file_type": "code",
      "source_file": "src/app/api/transactions/route.ts",
      "source_location": "L5",
      "id": "transactions_route_get",
      "community": 11,
      "norm_label": "get()"
    },
    {
      "label": "route.ts",
      "file_type": "code",
      "source_file": "src/app/api/transactions/delete/route.ts",
      "source_location": "L1",
      "id": "src_app_api_transactions_delete_route_ts",
      "community": 12,
      "norm_label": "route.ts"
    },
    {
      "label": "POST()",
      "file_type": "code",
      "source_file": "src/app/api/transactions/delete/route.ts",
      "source_location": "L5",
      "id": "delete_route_post",
      "community": 12,
      "norm_label": "post()"
    },
    {
      "label": "route.ts",
      "file_type": "code",
      "source_file": "src/app/api/transactions/add/route.ts",
      "source_location": "L1",
      "id": "src_app_api_transactions_add_route_ts",
      "community": 13,
      "norm_label": "route.ts"
    },
    {
      "label": "POST()",
      "file_type": "code",
      "source_file": "src/app/api/transactions/add/route.ts",
      "source_location": "L5",
      "id": "add_route_post",
      "community": 13,
      "norm_label": "post()"
    },
    {
      "label": "route.ts",
      "file_type": "code",
      "source_file": "src/app/api/sheets/create/route.ts",
      "source_location": "L1",
      "id": "src_app_api_sheets_create_route_ts",
      "community": 14,
      "norm_label": "route.ts"
    },
    {
      "label": "POST()",
      "file_type": "code",
      "source_file": "src/app/api/sheets/create/route.ts",
      "source_location": "L5",
      "id": "create_route_post",
      "community": 14,
      "norm_label": "post()"
    },
    {
      "label": "route.ts",
      "file_type": "code",
      "source_file": "src/app/api/sheets/details/route.ts",
      "source_location": "L1",
      "id": "src_app_api_sheets_details_route_ts",
      "community": 15,
      "norm_label": "route.ts"
    },
    {
      "label": "GET()",
      "file_type": "code",
      "source_file": "src/app/api/sheets/details/route.ts",
      "source_location": "L5",
      "id": "details_route_get",
      "community": 15,
      "norm_label": "get()"
    },
    {
      "label": "route.ts",
      "file_type": "code",
      "source_file": "src/app/api/sheets/select/route.ts",
      "source_location": "L1",
      "id": "src_app_api_sheets_select_route_ts",
      "community": 16,
      "norm_label": "route.ts"
    },
    {
      "label": "POST()",
      "file_type": "code",
      "source_file": "src/app/api/sheets/select/route.ts",
      "source_location": "L5",
      "id": "select_route_post",
      "community": 16,
      "norm_label": "post()"
    },
    {
      "label": "route.ts",
      "file_type": "code",
      "source_file": "src/app/api/sheets/list/route.ts",
      "source_location": "L1",
      "id": "src_app_api_sheets_list_route_ts",
      "community": 17,
      "norm_label": "route.ts"
    },
    {
      "label": "GET()",
      "file_type": "code",
      "source_file": "src/app/api/sheets/list/route.ts",
      "source_location": "L5",
      "id": "list_route_get",
      "community": 17,
      "norm_label": "get()"
    },
    {
      "label": "route.ts",
      "file_type": "code",
      "source_file": "src/app/api/config/route.ts",
      "source_location": "L1",
      "id": "src_app_api_config_route_ts",
      "community": 18,
      "norm_label": "route.ts"
    },
    {
      "label": "GET()",
      "file_type": "code",
      "source_file": "src/app/api/config/route.ts",
      "source_location": "L5",
      "id": "config_route_get",
      "community": 18,
      "norm_label": "get()"
    },
    {
      "label": "route.ts",
      "file_type": "code",
      "source_file": "src/app/api/config/update/route.ts",
      "source_location": "L1",
      "id": "src_app_api_config_update_route_ts",
      "community": 1,
      "norm_label": "route.ts"
    },
    {
      "label": "POST()",
      "file_type": "code",
      "source_file": "src/app/api/config/update/route.ts",
      "source_location": "L5",
      "id": "update_route_post",
      "community": 1,
      "norm_label": "post()"
    },
    {
      "label": "SheetSelector.tsx",
      "file_type": "code",
      "source_file": "src/components/sheets/SheetSelector.tsx",
      "source_location": "L1",
      "id": "src_components_sheets_sheetselector_tsx",
      "community": 19,
      "norm_label": "sheetselector.tsx"
    },
    {
      "label": "SheetsIcon()",
      "file_type": "code",
      "source_file": "src/components/sheets/SheetSelector.tsx",
      "source_location": "L15",
      "id": "sheets_sheetselector_sheetsicon",
      "community": 19,
      "norm_label": "sheetsicon()"
    },
    {
      "label": "OverviewTab.tsx",
      "file_type": "code",
      "source_file": "src/components/dashboard/OverviewTab.tsx",
      "source_location": "L1",
      "id": "src_components_dashboard_overviewtab_tsx",
      "community": 6,
      "norm_label": "overviewtab.tsx"
    },
    {
      "label": "fmt()",
      "file_type": "code",
      "source_file": "src/components/dashboard/OverviewTab.tsx",
      "source_location": "L12",
      "id": "dashboard_overviewtab_fmt",
      "community": 6,
      "norm_label": "fmt()"
    },
    {
      "label": "handleSaveIncomeOverride()",
      "file_type": "code",
      "source_file": "src/components/dashboard/OverviewTab.tsx",
      "source_location": "L172",
      "id": "dashboard_overviewtab_handlesaveincomeoverride",
      "community": 6,
      "norm_label": "handlesaveincomeoverride()"
    },
    {
      "label": "handleSaveFixedItem()",
      "file_type": "code",
      "source_file": "src/components/dashboard/OverviewTab.tsx",
      "source_location": "L188",
      "id": "dashboard_overviewtab_handlesavefixeditem",
      "community": 6,
      "norm_label": "handlesavefixeditem()"
    },
    {
      "label": "handleResetAllFixed()",
      "file_type": "code",
      "source_file": "src/components/dashboard/OverviewTab.tsx",
      "source_location": "L206",
      "id": "dashboard_overviewtab_handleresetallfixed",
      "community": 6,
      "norm_label": "handleresetallfixed()"
    },
    {
      "label": "dayLabel()",
      "file_type": "code",
      "source_file": "src/components/dashboard/OverviewTab.tsx",
      "source_location": "L227",
      "id": "dashboard_overviewtab_daylabel",
      "community": 6,
      "norm_label": "daylabel()"
    },
    {
      "label": "SettingsTab.tsx",
      "file_type": "code",
      "source_file": "/home/peter/Budget/src/components/dashboard/SettingsTab.tsx",
      "source_location": "L1",
      "id": "home_peter_budget_src_components_dashboard_settingstab_tsx",
      "community": 3,
      "norm_label": "settingstab.tsx"
    },
    {
      "label": "PencilBtn()",
      "file_type": "code",
      "source_file": "/home/peter/Budget/src/components/dashboard/SettingsTab.tsx",
      "source_location": "L18",
      "id": "dashboard_settingstab_pencilbtn",
      "community": 3,
      "norm_label": "pencilbtn()"
    },
    {
      "label": "DeleteBtn()",
      "file_type": "code",
      "source_file": "/home/peter/Budget/src/components/dashboard/SettingsTab.tsx",
      "source_location": "L44",
      "id": "dashboard_settingstab_deletebtn",
      "community": 3,
      "norm_label": "deletebtn()"
    },
    {
      "label": "handleAdd()",
      "file_type": "code",
      "source_file": "/home/peter/Budget/src/components/dashboard/SettingsTab.tsx",
      "source_location": "L70",
      "id": "dashboard_settingstab_handleadd",
      "community": 3,
      "norm_label": "handleadd()"
    },
    {
      "label": "handleDelete()",
      "file_type": "code",
      "source_file": "/home/peter/Budget/src/components/dashboard/SettingsTab.tsx",
      "source_location": "L79",
      "id": "dashboard_settingstab_handledelete",
      "community": 3,
      "norm_label": "handledelete()"
    },
    {
      "label": "startEdit()",
      "file_type": "code",
      "source_file": "/home/peter/Budget/src/components/dashboard/SettingsTab.tsx",
      "source_location": "L85",
      "id": "dashboard_settingstab_startedit",
      "community": 3,
      "norm_label": "startedit()"
    },
    {
      "label": "saveEdit()",
      "file_type": "code",
      "source_file": "/home/peter/Budget/src/components/dashboard/SettingsTab.tsx",
      "source_location": "L90",
      "id": "dashboard_settingstab_saveedit",
      "community": 3,
      "norm_label": "saveedit()"
    },
    {
      "label": "handleAmountChange()",
      "file_type": "code",
      "source_file": "/home/peter/Budget/src/components/dashboard/SettingsTab.tsx",
      "source_location": "L172",
      "id": "dashboard_settingstab_handleamountchange",
      "community": 3,
      "norm_label": "handleamountchange()"
    },
    {
      "label": "handlePctChange()",
      "file_type": "code",
      "source_file": "/home/peter/Budget/src/components/dashboard/SettingsTab.tsx",
      "source_location": "L181",
      "id": "dashboard_settingstab_handlepctchange",
      "community": 3,
      "norm_label": "handlepctchange()"
    },
    {
      "label": "fmtAmt()",
      "file_type": "code",
      "source_file": "/home/peter/Budget/src/components/dashboard/SettingsTab.tsx",
      "source_location": "L220",
      "id": "dashboard_settingstab_fmtamt",
      "community": 3,
      "norm_label": "fmtamt()"
    },
    {
      "label": "toPct()",
      "file_type": "code",
      "source_file": "/home/peter/Budget/src/components/dashboard/SettingsTab.tsx",
      "source_location": "L221",
      "id": "dashboard_settingstab_topct",
      "community": 3,
      "norm_label": "topct()"
    },
    {
      "label": "handleSaveIncome()",
      "file_type": "code",
      "source_file": "/home/peter/Budget/src/components/dashboard/SettingsTab.tsx",
      "source_location": "L418",
      "id": "dashboard_settingstab_handlesaveincome",
      "community": 3,
      "norm_label": "handlesaveincome()"
    },
    {
      "label": "EverythingTab.tsx",
      "file_type": "code",
      "source_file": "src/components/dashboard/EverythingTab.tsx",
      "source_location": "L1",
      "id": "src_components_dashboard_everythingtab_tsx",
      "community": 5,
      "norm_label": "everythingtab.tsx"
    },
    {
      "label": "fmt()",
      "file_type": "code",
      "source_file": "src/components/dashboard/EverythingTab.tsx",
      "source_location": "L15",
      "id": "dashboard_everythingtab_fmt",
      "community": 5,
      "norm_label": "fmt()"
    },
    {
      "label": "yAxisFmt()",
      "file_type": "code",
      "source_file": "src/components/dashboard/EverythingTab.tsx",
      "source_location": "L19",
      "id": "dashboard_everythingtab_yaxisfmt",
      "community": 5,
      "norm_label": "yaxisfmt()"
    },
    {
      "label": "keyToShortLabel()",
      "file_type": "code",
      "source_file": "src/components/dashboard/EverythingTab.tsx",
      "source_location": "L23",
      "id": "dashboard_everythingtab_keytoshortlabel",
      "community": 5,
      "norm_label": "keytoshortlabel()"
    },
    {
      "label": "keyToFullLabel()",
      "file_type": "code",
      "source_file": "src/components/dashboard/EverythingTab.tsx",
      "source_location": "L28",
      "id": "dashboard_everythingtab_keytofulllabel",
      "community": 5,
      "norm_label": "keytofulllabel()"
    },
    {
      "label": "handleClick()",
      "file_type": "code",
      "source_file": "src/components/dashboard/EverythingTab.tsx",
      "source_location": "L65",
      "id": "dashboard_everythingtab_handleclick",
      "community": 5,
      "norm_label": "handleclick()"
    },
    {
      "label": "toggleSort()",
      "file_type": "code",
      "source_file": "src/components/dashboard/EverythingTab.tsx",
      "source_location": "L148",
      "id": "dashboard_everythingtab_togglesort",
      "community": 5,
      "norm_label": "togglesort()"
    },
    {
      "label": "toggleMonth()",
      "file_type": "code",
      "source_file": "src/components/dashboard/EverythingTab.tsx",
      "source_location": "L153",
      "id": "dashboard_everythingtab_togglemonth",
      "community": 5,
      "norm_label": "togglemonth()"
    },
    {
      "label": "TransactionsTab.tsx",
      "file_type": "code",
      "source_file": "/home/peter/Budget/src/components/dashboard/TransactionsTab.tsx",
      "source_location": "L1",
      "id": "home_peter_budget_src_components_dashboard_transactionstab_tsx",
      "community": 4,
      "norm_label": "transactionstab.tsx"
    },
    {
      "label": "fmt()",
      "file_type": "code",
      "source_file": "/home/peter/Budget/src/components/dashboard/TransactionsTab.tsx",
      "source_location": "L9",
      "id": "dashboard_transactionstab_fmt",
      "community": 4,
      "norm_label": "fmt()"
    },
    {
      "label": "todayISO()",
      "file_type": "code",
      "source_file": "/home/peter/Budget/src/components/dashboard/TransactionsTab.tsx",
      "source_location": "L13",
      "id": "dashboard_transactionstab_todayiso",
      "community": 4,
      "norm_label": "todayiso()"
    },
    {
      "label": "clearFilters()",
      "file_type": "code",
      "source_file": "/home/peter/Budget/src/components/dashboard/TransactionsTab.tsx",
      "source_location": "L103",
      "id": "dashboard_transactionstab_clearfilters",
      "community": 4,
      "norm_label": "clearfilters()"
    },
    {
      "label": "prevMonth()",
      "file_type": "code",
      "source_file": "/home/peter/Budget/src/components/dashboard/TransactionsTab.tsx",
      "source_location": "L110",
      "id": "dashboard_transactionstab_prevmonth",
      "community": 4,
      "norm_label": "prevmonth()"
    },
    {
      "label": "nextMonth()",
      "file_type": "code",
      "source_file": "/home/peter/Budget/src/components/dashboard/TransactionsTab.tsx",
      "source_location": "L117",
      "id": "dashboard_transactionstab_nextmonth",
      "community": 4,
      "norm_label": "nextmonth()"
    },
    {
      "label": "handleAdd()",
      "file_type": "code",
      "source_file": "/home/peter/Budget/src/components/dashboard/TransactionsTab.tsx",
      "source_location": "L125",
      "id": "dashboard_transactionstab_handleadd",
      "community": 4,
      "norm_label": "handleadd()"
    },
    {
      "label": "handleDelete()",
      "file_type": "code",
      "source_file": "/home/peter/Budget/src/components/dashboard/TransactionsTab.tsx",
      "source_location": "L144",
      "id": "dashboard_transactionstab_handledelete",
      "community": 4,
      "norm_label": "handledelete()"
    },
    {
      "label": "onDown()",
      "file_type": "code",
      "source_file": "/home/peter/Budget/src/components/dashboard/TransactionsTab.tsx",
      "source_location": "L165",
      "id": "dashboard_transactionstab_ondown",
      "community": 4,
      "norm_label": "ondown()"
    },
    {
      "label": "google-identity.d.ts",
      "file_type": "code",
      "source_file": "types/google-identity.d.ts",
      "source_location": "L1",
      "id": "types_google_identity_d_ts",
      "community": 24,
      "norm_label": "google-identity.d.ts"
    }
  ],
  "links": [
    {
      "relation": "contains",
      "confidence": "EXTRACTED",
      "source_file": "src/lib/hooks/useGoogleOAuth.ts",
      "source_location": "L19",
      "weight": 1.0,
      "_src": "src_lib_hooks_usegoogleoauth_ts",
      "_tgt": "hooks_usegoogleoauth_loadgooglesdk",
      "source": "src_lib_hooks_usegoogleoauth_ts",
      "target": "hooks_usegoogleoauth_loadgooglesdk",
      "confidence_score": 1.0
    },
    {
      "relation": "contains",
      "confidence": "EXTRACTED",
      "source_file": "src/lib/hooks/useGoogleOAuth.ts",
      "source_location": "L32",
      "weight": 1.0,
      "_src": "src_lib_hooks_usegoogleoauth_ts",
      "_tgt": "hooks_usegoogleoauth_usegoogleoauth",
      "source": "src_lib_hooks_usegoogleoauth_ts",
      "target": "hooks_usegoogleoauth_usegoogleoauth",
      "confidence_score": 1.0
    },
    {
      "relation": "contains",
      "confidence": "EXTRACTED",
      "source_file": "src/lib/google/sheets.ts",
      "source_location": "L29",
      "weight": 1.0,
      "_src": "src_lib_google_sheets_ts",
      "_tgt": "google_sheets_sectiondataend",
      "source": "src_lib_google_sheets_ts",
      "target": "google_sheets_sectiondataend",
      "confidence_score": 1.0
    },
    {
      "relation": "contains",
      "confidence": "EXTRACTED",
      "source_file": "src/lib/google/sheets.ts",
      "source_location": "L39",
      "weight": 1.0,
      "_src": "src_lib_google_sheets_ts",
      "_tgt": "google_sheets_quotesheet",
      "source": "src_lib_google_sheets_ts",
      "target": "google_sheets_quotesheet",
      "confidence_score": 1.0
    },
    {
      "relation": "contains",
      "confidence": "EXTRACTED",
      "source_file": "src/lib/google/sheets.ts",
      "source_location": "L43",
      "weight": 1.0,
      "_src": "src_lib_google_sheets_ts",
      "_tgt": "google_sheets_getmonthlabel",
      "source": "src_lib_google_sheets_ts",
      "target": "google_sheets_getmonthlabel",
      "confidence_score": 1.0
    },
    {
      "relation": "contains",
      "confidence": "EXTRACTED",
      "source_file": "src/lib/google/sheets.ts",
      "source_location": "L50",
      "weight": 1.0,
      "_src": "src_lib_google_sheets_ts",
      "_tgt": "google_sheets_monthlabeltonum",
      "source": "src_lib_google_sheets_ts",
      "target": "google_sheets_monthlabeltonum",
      "confidence_score": 1.0
    },
    {
      "relation": "contains",
      "confidence": "EXTRACTED",
      "source_file": "src/lib/google/sheets.ts",
      "source_location": "L55",
      "weight": 1.0,
      "_src": "src_lib_google_sheets_ts",
      "_tgt": "google_sheets_currentmonthlabel",
      "source": "src_lib_google_sheets_ts",
      "target": "google_sheets_currentmonthlabel",
      "confidence_score": 1.0
    },
    {
      "relation": "contains",
      "confidence": "EXTRACTED",
      "source_file": "src/lib/google/sheets.ts",
      "source_location": "L60",
      "weight": 1.0,
      "_src": "src_lib_google_sheets_ts",
      "_tgt": "google_sheets_sheetsservice",
      "source": "src_lib_google_sheets_ts",
      "target": "google_sheets_sheetsservice",
      "confidence_score": 1.0
    },
    {
      "relation": "calls",
      "confidence": "EXTRACTED",
      "source_file": "src/lib/google/sheets.ts",
      "source_location": "L309",
      "weight": 1.0,
      "_src": "google_sheets_sheetsservice_addconfigitem",
      "_tgt": "google_sheets_sectiondataend",
      "source": "google_sheets_sectiondataend",
      "target": "google_sheets_sheetsservice_addconfigitem",
      "confidence_score": 1.0
    },
    {
      "relation": "calls",
      "confidence": "EXTRACTED",
      "source_file": "src/lib/google/sheets.ts",
      "source_location": "L657",
      "weight": 1.0,
      "_src": "google_sheets_sheetsservice_setmanymonthlyincomeoverrides",
      "_tgt": "google_sheets_sectiondataend",
      "source": "google_sheets_sectiondataend",
      "target": "google_sheets_sheetsservice_setmanymonthlyincomeoverrides",
      "confidence_score": 1.0
    },
    {
      "relation": "calls",
      "confidence": "EXTRACTED",
      "source_file": "src/lib/google/sheets.ts",
      "source_location": "L692",
      "weight": 1.0,
      "_src": "google_sheets_sheetsservice_setmanyfixedexpenseoverrides",
      "_tgt": "google_sheets_sectiondataend",
      "source": "google_sheets_sectiondataend",
      "target": "google_sheets_sheetsservice_setmanyfixedexpenseoverrides",
      "confidence_score": 1.0
    },
    {
      "relation": "calls",
      "confidence": "EXTRACTED",
      "source_file": "src/lib/google/sheets.ts",
      "source_location": "L735",
      "weight": 1.0,
      "_src": "google_sheets_sheetsservice_setmonthlyincomeoverride",
      "_tgt": "google_sheets_sectiondataend",
      "source": "google_sheets_sectiondataend",
      "target": "google_sheets_sheetsservice_setmonthlyincomeoverride",
      "confidence_score": 1.0
    },
    {
      "relation": "calls",
      "confidence": "EXTRACTED",
      "source_file": "src/lib/google/sheets.ts",
      "source_location": "L779",
      "weight": 1.0,
      "_src": "google_sheets_sheetsservice_deletemonthlyincomeoverride",
      "_tgt": "google_sheets_sectiondataend",
      "source": "google_sheets_sectiondataend",
      "target": "google_sheets_sheetsservice_deletemonthlyincomeoverride",
      "confidence_score": 1.0
    },
    {
      "relation": "calls",
      "confidence": "EXTRACTED",
      "source_file": "src/lib/google/sheets.ts",
      "source_location": "L815",
      "weight": 1.0,
      "_src": "google_sheets_sheetsservice_setfixedexpenseoverride",
      "_tgt": "google_sheets_sectiondataend",
      "source": "google_sheets_sectiondataend",
      "target": "google_sheets_sheetsservice_setfixedexpenseoverride",
      "confidence_score": 1.0
    },
    {
      "relation": "calls",
      "confidence": "EXTRACTED",
      "source_file": "src/lib/google/sheets.ts",
      "source_location": "L860",
      "weight": 1.0,
      "_src": "google_sheets_sheetsservice_deletefixedexpenseoverride",
      "_tgt": "google_sheets_sectiondataend",
      "source": "google_sheets_sectiondataend",
      "target": "google_sheets_sheetsservice_deletefixedexpenseoverride",
      "confidence_score": 1.0
    },
    {
      "relation": "calls",
      "confidence": "EXTRACTED",
      "source_file": "src/lib/google/sheets.ts",
      "source_location": "L454",
      "weight": 1.0,
      "_src": "google_sheets_sheetsservice_syncfixedexpensestomonthsheet",
      "_tgt": "google_sheets_quotesheet",
      "source": "google_sheets_quotesheet",
      "target": "google_sheets_sheetsservice_syncfixedexpensestomonthsheet",
      "confidence_score": 1.0
    },
    {
      "relation": "calls",
      "confidence": "EXTRACTED",
      "source_file": "src/lib/google/sheets.ts",
      "source_location": "L540",
      "weight": 1.0,
      "_src": "google_sheets_sheetsservice_createmonthsheet",
      "_tgt": "google_sheets_quotesheet",
      "source": "google_sheets_quotesheet",
      "target": "google_sheets_sheetsservice_createmonthsheet",
      "confidence_score": 1.0
    },
    {
      "relation": "calls",
      "confidence": "EXTRACTED",
      "source_file": "src/lib/google/sheets.ts",
      "source_location": "L601",
      "weight": 1.0,
      "_src": "google_sheets_sheetsservice_readtransactions",
      "_tgt": "google_sheets_quotesheet",
      "source": "google_sheets_quotesheet",
      "target": "google_sheets_sheetsservice_readtransactions",
      "confidence_score": 1.0
    },
    {
      "relation": "calls",
      "confidence": "EXTRACTED",
      "source_file": "src/lib/google/sheets.ts",
      "source_location": "L902",
      "weight": 1.0,
      "_src": "google_sheets_sheetsservice_addtransaction",
      "_tgt": "google_sheets_quotesheet",
      "source": "google_sheets_quotesheet",
      "target": "google_sheets_sheetsservice_addtransaction",
      "confidence_score": 1.0
    },
    {
      "relation": "calls",
      "confidence": "EXTRACTED",
      "source_file": "src/lib/google/sheets.ts",
      "source_location": "L884",
      "weight": 1.0,
      "_src": "google_sheets_sheetsservice_addtransaction",
      "_tgt": "google_sheets_getmonthlabel",
      "source": "google_sheets_getmonthlabel",
      "target": "google_sheets_sheetsservice_addtransaction",
      "confidence_score": 1.0
    },
    {
      "relation": "calls",
      "confidence": "EXTRACTED",
      "source_file": "src/lib/google/sheets.ts",
      "source_location": "L431",
      "weight": 1.0,
      "_src": "google_sheets_sheetsservice_syncfixedexpensestoallmonthsheets",
      "_tgt": "google_sheets_monthlabeltonum",
      "source": "google_sheets_monthlabeltonum",
      "target": "google_sheets_sheetsservice_syncfixedexpensestoallmonthsheets",
      "confidence_score": 1.0
    },
    {
      "relation": "calls",
      "confidence": "INFERRED",
      "confidence_score": 0.8,
      "source_file": "src/app/api/config/update/route.ts",
      "source_location": "L20",
      "weight": 1.0,
      "_src": "google_sheets_currentmonthlabel",
      "_tgt": "update_route_post",
      "source": "google_sheets_currentmonthlabel",
      "target": "update_route_post"
    },
    {
      "relation": "method",
      "confidence": "EXTRACTED",
      "source_file": "src/lib/google/sheets.ts",
      "source_location": "L64",
      "weight": 1.0,
      "_src": "google_sheets_sheetsservice",
      "_tgt": "google_sheets_sheetsservice_constructor",
      "source": "google_sheets_sheetsservice",
      "target": "google_sheets_sheetsservice_constructor",
      "confidence_score": 1.0
    },
    {
      "relation": "method",
      "confidence": "EXTRACTED",
      "source_file": "src/lib/google/sheets.ts",
      "source_location": "L69",
      "weight": 1.0,
      "_src": "google_sheets_sheetsservice",
      "_tgt": "google_sheets_sheetsservice_listsheets",
      "source": "google_sheets_sheetsservice",
      "target": "google_sheets_sheetsservice_listsheets",
      "confidence_score": 1.0
    },
    {
      "relation": "method",
      "confidence": "EXTRACTED",
      "source_file": "src/lib/google/sheets.ts",
      "source_location": "L92",
      "weight": 1.0,
      "_src": "google_sheets_sheetsservice",
      "_tgt": "google_sheets_sheetsservice_createbudgetsheet",
      "source": "google_sheets_sheetsservice",
      "target": "google_sheets_sheetsservice_createbudgetsheet",
      "confidence_score": 1.0
    },
    {
      "relation": "method",
      "confidence": "EXTRACTED",
      "source_file": "src/lib/google/sheets.ts",
      "source_location": "L155",
      "weight": 1.0,
      "_src": "google_sheets_sheetsservice",
      "_tgt": "google_sheets_sheetsservice_validatesheet",
      "source": "google_sheets_sheetsservice",
      "target": "google_sheets_sheetsservice_validatesheet",
      "confidence_score": 1.0
    },
    {
      "relation": "method",
      "confidence": "EXTRACTED",
      "source_file": "src/lib/google/sheets.ts",
      "source_location": "L174",
      "weight": 1.0,
      "_src": "google_sheets_sheetsservice",
      "_tgt": "google_sheets_sheetsservice_getsheetdetails",
      "source": "google_sheets_sheetsservice",
      "target": "google_sheets_sheetsservice_getsheetdetails",
      "confidence_score": 1.0
    },
    {
      "relation": "method",
      "confidence": "EXTRACTED",
      "source_file": "src/lib/google/sheets.ts",
      "source_location": "L190",
      "weight": 1.0,
      "_src": "google_sheets_sheetsservice",
      "_tgt": "google_sheets_sheetsservice_getconfigsheetnumericid",
      "source": "google_sheets_sheetsservice",
      "target": "google_sheets_sheetsservice_getconfigsheetnumericid",
      "confidence_score": 1.0
    },
    {
      "relation": "method",
      "confidence": "EXTRACTED",
      "source_file": "src/lib/google/sheets.ts",
      "source_location": "L195",
      "weight": 1.0,
      "_src": "google_sheets_sheetsservice",
      "_tgt": "google_sheets_sheetsservice_readconfig",
      "source": "google_sheets_sheetsservice",
      "target": "google_sheets_sheetsservice_readconfig",
      "confidence_score": 1.0
    },
    {
      "relation": "method",
      "confidence": "EXTRACTED",
      "source_file": "src/lib/google/sheets.ts",
      "source_location": "L291",
      "weight": 1.0,
      "_src": "google_sheets_sheetsservice",
      "_tgt": "google_sheets_sheetsservice_addconfigitem",
      "source": "google_sheets_sheetsservice",
      "target": "google_sheets_sheetsservice_addconfigitem",
      "confidence_score": 1.0
    },
    {
      "relation": "method",
      "confidence": "EXTRACTED",
      "source_file": "src/lib/google/sheets.ts",
      "source_location": "L362",
      "weight": 1.0,
      "_src": "google_sheets_sheetsservice",
      "_tgt": "google_sheets_sheetsservice_updateconfigitem",
      "source": "google_sheets_sheetsservice",
      "target": "google_sheets_sheetsservice_updateconfigitem",
      "confidence_score": 1.0
    },
    {
      "relation": "method",
      "confidence": "EXTRACTED",
      "source_file": "src/lib/google/sheets.ts",
      "source_location": "L391",
      "weight": 1.0,
      "_src": "google_sheets_sheetsservice",
      "_tgt": "google_sheets_sheetsservice_deleteconfigitem",
      "source": "google_sheets_sheetsservice",
      "target": "google_sheets_sheetsservice_deleteconfigitem",
      "confidence_score": 1.0
    },
    {
      "relation": "method",
      "confidence": "EXTRACTED",
      "source_file": "src/lib/google/sheets.ts",
      "source_location": "L422",
      "weight": 1.0,
      "_src": "google_sheets_sheetsservice",
      "_tgt": "google_sheets_sheetsservice_syncfixedexpensestoallmonthsheets",
      "source": "google_sheets_sheetsservice",
      "target": "google_sheets_sheetsservice_syncfixedexpensestoallmonthsheets",
      "confidence_score": 1.0
    },
    {
      "relation": "method",
      "confidence": "EXTRACTED",
      "source_file": "src/lib/google/sheets.ts",
      "source_location": "L446",
      "weight": 1.0,
      "_src": "google_sheets_sheetsservice",
      "_tgt": "google_sheets_sheetsservice_syncfixedexpensestomonthsheet",
      "source": "google_sheets_sheetsservice",
      "target": "google_sheets_sheetsservice_syncfixedexpensestomonthsheet",
      "confidence_score": 1.0
    },
    {
      "relation": "method",
      "confidence": "EXTRACTED",
      "source_file": "src/lib/google/sheets.ts",
      "source_location": "L514",
      "weight": 1.0,
      "_src": "google_sheets_sheetsservice",
      "_tgt": "google_sheets_sheetsservice_createmonthsheet",
      "source": "google_sheets_sheetsservice",
      "target": "google_sheets_sheetsservice_createmonthsheet",
      "confidence_score": 1.0
    },
    {
      "relation": "method",
      "confidence": "EXTRACTED",
      "source_file": "src/lib/google/sheets.ts",
      "source_location": "L583",
      "weight": 1.0,
      "_src": "google_sheets_sheetsservice",
      "_tgt": "google_sheets_sheetsservice_readtransactions",
      "source": "google_sheets_sheetsservice",
      "target": "google_sheets_sheetsservice_readtransactions",
      "confidence_score": 1.0
    },
    {
      "relation": "method",
      "confidence": "EXTRACTED",
      "source_file": "src/lib/google/sheets.ts",
      "source_location": "L642",
      "weight": 1.0,
      "_src": "google_sheets_sheetsservice",
      "_tgt": "google_sheets_sheetsservice_setmanymonthlyincomeoverrides",
      "source": "google_sheets_sheetsservice",
      "target": "google_sheets_sheetsservice_setmanymonthlyincomeoverrides",
      "confidence_score": 1.0
    },
    {
      "relation": "method",
      "confidence": "EXTRACTED",
      "source_file": "src/lib/google/sheets.ts",
      "source_location": "L677",
      "weight": 1.0,
      "_src": "google_sheets_sheetsservice",
      "_tgt": "google_sheets_sheetsservice_setmanyfixedexpenseoverrides",
      "source": "google_sheets_sheetsservice",
      "target": "google_sheets_sheetsservice_setmanyfixedexpenseoverrides",
      "confidence_score": 1.0
    },
    {
      "relation": "method",
      "confidence": "EXTRACTED",
      "source_file": "src/lib/google/sheets.ts",
      "source_location": "L713",
      "weight": 1.0,
      "_src": "google_sheets_sheetsservice",
      "_tgt": "google_sheets_sheetsservice_setmonthlyincomeoverride",
      "source": "google_sheets_sheetsservice",
      "target": "google_sheets_sheetsservice_setmonthlyincomeoverride",
      "confidence_score": 1.0
    },
    {
      "relation": "method",
      "confidence": "EXTRACTED",
      "source_file": "src/lib/google/sheets.ts",
      "source_location": "L768",
      "weight": 1.0,
      "_src": "google_sheets_sheetsservice",
      "_tgt": "google_sheets_sheetsservice_deletemonthlyincomeoverride",
      "source": "google_sheets_sheetsservice",
      "target": "google_sheets_sheetsservice_deletemonthlyincomeoverride",
      "confidence_score": 1.0
    },
    {
      "relation": "method",
      "confidence": "EXTRACTED",
      "source_file": "src/lib/google/sheets.ts",
      "source_location": "L793",
      "weight": 1.0,
      "_src": "google_sheets_sheetsservice",
      "_tgt": "google_sheets_sheetsservice_setfixedexpenseoverride",
      "source": "google_sheets_sheetsservice",
      "target": "google_sheets_sheetsservice_setfixedexpenseoverride",
      "confidence_score": 1.0
    },
    {
      "relation": "method",
      "confidence": "EXTRACTED",
      "source_file": "src/lib/google/sheets.ts",
      "source_location": "L849",
      "weight": 1.0,
      "_src": "google_sheets_sheetsservice",
      "_tgt": "google_sheets_sheetsservice_deletefixedexpenseoverride",
      "source": "google_sheets_sheetsservice",
      "target": "google_sheets_sheetsservice_deletefixedexpenseoverride",
      "confidence_score": 1.0
    },
    {
      "relation": "method",
      "confidence": "EXTRACTED",
      "source_file": "src/lib/google/sheets.ts",
      "source_location": "L875",
      "weight": 1.0,
      "_src": "google_sheets_sheetsservice",
      "_tgt": "google_sheets_sheetsservice_addtransaction",
      "source": "google_sheets_sheetsservice",
      "target": "google_sheets_sheetsservice_addtransaction",
      "confidence_score": 1.0
    },
    {
      "relation": "method",
      "confidence": "EXTRACTED",
      "source_file": "src/lib/google/sheets.ts",
      "source_location": "L914",
      "weight": 1.0,
      "_src": "google_sheets_sheetsservice",
      "_tgt": "google_sheets_sheetsservice_deletetransaction",
      "source": "google_sheets_sheetsservice",
      "target": "google_sheets_sheetsservice_deletetransaction",
      "confidence_score": 1.0
    },
    {
      "relation": "calls",
      "confidence": "EXTRACTED",
      "source_file": "src/lib/google/sheets.ts",
      "source_location": "L666",
      "weight": 1.0,
      "_src": "google_sheets_sheetsservice_setmanymonthlyincomeoverrides",
      "_tgt": "google_sheets_sheetsservice_getconfigsheetnumericid",
      "source": "google_sheets_sheetsservice_getconfigsheetnumericid",
      "target": "google_sheets_sheetsservice_setmanymonthlyincomeoverrides",
      "confidence_score": 1.0
    },
    {
      "relation": "calls",
      "confidence": "EXTRACTED",
      "source_file": "src/lib/google/sheets.ts",
      "source_location": "L702",
      "weight": 1.0,
      "_src": "google_sheets_sheetsservice_setmanyfixedexpenseoverrides",
      "_tgt": "google_sheets_sheetsservice_getconfigsheetnumericid",
      "source": "google_sheets_sheetsservice_getconfigsheetnumericid",
      "target": "google_sheets_sheetsservice_setmanyfixedexpenseoverrides",
      "confidence_score": 1.0
    },
    {
      "relation": "calls",
      "confidence": "EXTRACTED",
      "source_file": "src/lib/google/sheets.ts",
      "source_location": "L749",
      "weight": 1.0,
      "_src": "google_sheets_sheetsservice_setmonthlyincomeoverride",
      "_tgt": "google_sheets_sheetsservice_getconfigsheetnumericid",
      "source": "google_sheets_sheetsservice_getconfigsheetnumericid",
      "target": "google_sheets_sheetsservice_setmonthlyincomeoverride",
      "confidence_score": 1.0
    },
    {
      "relation": "calls",
      "confidence": "EXTRACTED",
      "source_file": "src/lib/google/sheets.ts",
      "source_location": "L830",
      "weight": 1.0,
      "_src": "google_sheets_sheetsservice_setfixedexpenseoverride",
      "_tgt": "google_sheets_sheetsservice_getconfigsheetnumericid",
      "source": "google_sheets_sheetsservice_getconfigsheetnumericid",
      "target": "google_sheets_sheetsservice_setfixedexpenseoverride",
      "confidence_score": 1.0
    },
    {
      "relation": "calls",
      "confidence": "EXTRACTED",
      "source_file": "src/lib/google/sheets.ts",
      "source_location": "L896",
      "weight": 1.0,
      "_src": "google_sheets_sheetsservice_addtransaction",
      "_tgt": "google_sheets_sheetsservice_readconfig",
      "source": "google_sheets_sheetsservice_readconfig",
      "target": "google_sheets_sheetsservice_addtransaction",
      "confidence_score": 1.0
    },
    {
      "relation": "calls",
      "confidence": "EXTRACTED",
      "source_file": "src/lib/google/sheets.ts",
      "source_location": "L783",
      "weight": 1.0,
      "_src": "google_sheets_sheetsservice_deletemonthlyincomeoverride",
      "_tgt": "google_sheets_sheetsservice_deleteconfigitem",
      "source": "google_sheets_sheetsservice_deleteconfigitem",
      "target": "google_sheets_sheetsservice_deletemonthlyincomeoverride",
      "confidence_score": 1.0
    },
    {
      "relation": "calls",
      "confidence": "EXTRACTED",
      "source_file": "src/lib/google/sheets.ts",
      "source_location": "L865",
      "weight": 1.0,
      "_src": "google_sheets_sheetsservice_deletefixedexpenseoverride",
      "_tgt": "google_sheets_sheetsservice_deleteconfigitem",
      "source": "google_sheets_sheetsservice_deleteconfigitem",
      "target": "google_sheets_sheetsservice_deletefixedexpenseoverride",
      "confidence_score": 1.0
    },
    {
      "relation": "calls",
      "confidence": "EXTRACTED",
      "source_file": "src/lib/google/sheets.ts",
      "source_location": "L439",
      "weight": 1.0,
      "_src": "google_sheets_sheetsservice_syncfixedexpensestoallmonthsheets",
      "_tgt": "google_sheets_sheetsservice_syncfixedexpensestomonthsheet",
      "source": "google_sheets_sheetsservice_syncfixedexpensestoallmonthsheets",
      "target": "google_sheets_sheetsservice_syncfixedexpensestomonthsheet",
      "confidence_score": 1.0
    },
    {
      "relation": "calls",
      "confidence": "EXTRACTED",
      "source_file": "src/lib/google/sheets.ts",
      "source_location": "L897",
      "weight": 1.0,
      "_src": "google_sheets_sheetsservice_addtransaction",
      "_tgt": "google_sheets_sheetsservice_createmonthsheet",
      "source": "google_sheets_sheetsservice_createmonthsheet",
      "target": "google_sheets_sheetsservice_addtransaction",
      "confidence_score": 1.0
    },
    {
      "relation": "contains",
      "confidence": "EXTRACTED",
      "source_file": "src/app/layout.tsx",
      "source_location": "L21",
      "weight": 1.0,
      "_src": "src_app_layout_tsx",
      "_tgt": "app_layout_rootlayout",
      "source": "src_app_layout_tsx",
      "target": "app_layout_rootlayout",
      "confidence_score": 1.0
    },
    {
      "relation": "contains",
      "confidence": "EXTRACTED",
      "source_file": "src/app/page.tsx",
      "source_location": "L8",
      "weight": 1.0,
      "_src": "src_app_page_tsx",
      "_tgt": "app_page_googleg",
      "source": "src_app_page_tsx",
      "target": "app_page_googleg",
      "confidence_score": 1.0
    },
    {
      "relation": "contains",
      "confidence": "EXTRACTED",
      "source_file": "src/app/page.tsx",
      "source_location": "L30",
      "weight": 1.0,
      "_src": "src_app_page_tsx",
      "_tgt": "app_page_handlelogin",
      "source": "src_app_page_tsx",
      "target": "app_page_handlelogin",
      "confidence_score": 1.0
    },
    {
      "relation": "contains",
      "confidence": "EXTRACTED",
      "source_file": "src/app/sheets/select/page.tsx",
      "source_location": "L21",
      "weight": 1.0,
      "_src": "src_app_sheets_select_page_tsx",
      "_tgt": "select_page_ondown",
      "source": "src_app_sheets_select_page_tsx",
      "target": "select_page_ondown",
      "confidence_score": 1.0
    },
    {
      "relation": "contains",
      "confidence": "EXTRACTED",
      "source_file": "src/app/sheets/select/page.tsx",
      "source_location": "L42",
      "weight": 1.0,
      "_src": "src_app_sheets_select_page_tsx",
      "_tgt": "select_page_handleselectsheet",
      "source": "src_app_sheets_select_page_tsx",
      "target": "select_page_handleselectsheet",
      "confidence_score": 1.0
    },
    {
      "relation": "contains",
      "confidence": "EXTRACTED",
      "source_file": "src/app/sheets/select/page.tsx",
      "source_location": "L69",
      "weight": 1.0,
      "_src": "src_app_sheets_select_page_tsx",
      "_tgt": "select_page_handlecreatenew",
      "source": "src_app_sheets_select_page_tsx",
      "target": "select_page_handlecreatenew",
      "confidence_score": 1.0
    },
    {
      "relation": "contains",
      "confidence": "EXTRACTED",
      "source_file": "src/app/dashboard/page.tsx",
      "source_location": "L42",
      "weight": 1.0,
      "_src": "src_app_dashboard_page_tsx",
      "_tgt": "dashboard_page_ondown",
      "source": "src_app_dashboard_page_tsx",
      "target": "dashboard_page_ondown",
      "confidence_score": 1.0
    },
    {
      "relation": "contains",
      "confidence": "EXTRACTED",
      "source_file": "src/app/dashboard/page.tsx",
      "source_location": "L143",
      "weight": 1.0,
      "_src": "src_app_dashboard_page_tsx",
      "_tgt": "dashboard_page_getpastmonthkeys",
      "source": "src_app_dashboard_page_tsx",
      "target": "dashboard_page_getpastmonthkeys",
      "confidence_score": 1.0
    },
    {
      "relation": "contains",
      "confidence": "EXTRACTED",
      "source_file": "src/app/dashboard/page.tsx",
      "source_location": "L149",
      "weight": 1.0,
      "_src": "src_app_dashboard_page_tsx",
      "_tgt": "dashboard_page_handleconfigadd",
      "source": "src_app_dashboard_page_tsx",
      "target": "dashboard_page_handleconfigadd",
      "confidence_score": 1.0
    },
    {
      "relation": "contains",
      "confidence": "EXTRACTED",
      "source_file": "src/app/dashboard/page.tsx",
      "source_location": "L164",
      "weight": 1.0,
      "_src": "src_app_dashboard_page_tsx",
      "_tgt": "dashboard_page_handleconfigedit",
      "source": "src_app_dashboard_page_tsx",
      "target": "dashboard_page_handleconfigedit",
      "confidence_score": 1.0
    },
    {
      "relation": "contains",
      "confidence": "EXTRACTED",
      "source_file": "src/app/dashboard/page.tsx",
      "source_location": "L179",
      "weight": 1.0,
      "_src": "src_app_dashboard_page_tsx",
      "_tgt": "dashboard_page_handleconfigdelete",
      "source": "src_app_dashboard_page_tsx",
      "target": "dashboard_page_handleconfigdelete",
      "confidence_score": 1.0
    },
    {
      "relation": "contains",
      "confidence": "EXTRACTED",
      "source_file": "src/app/dashboard/page.tsx",
      "source_location": "L193",
      "weight": 1.0,
      "_src": "src_app_dashboard_page_tsx",
      "_tgt": "dashboard_page_handlesetincome",
      "source": "src_app_dashboard_page_tsx",
      "target": "dashboard_page_handlesetincome",
      "confidence_score": 1.0
    },
    {
      "relation": "contains",
      "confidence": "EXTRACTED",
      "source_file": "src/app/dashboard/page.tsx",
      "source_location": "L204",
      "weight": 1.0,
      "_src": "src_app_dashboard_page_tsx",
      "_tgt": "dashboard_page_handlesetmonthlyincomeoverride",
      "source": "src_app_dashboard_page_tsx",
      "target": "dashboard_page_handlesetmonthlyincomeoverride",
      "confidence_score": 1.0
    },
    {
      "relation": "contains",
      "confidence": "EXTRACTED",
      "source_file": "src/app/dashboard/page.tsx",
      "source_location": "L220",
      "weight": 1.0,
      "_src": "src_app_dashboard_page_tsx",
      "_tgt": "dashboard_page_handledeletemonthlyincomeoverride",
      "source": "src_app_dashboard_page_tsx",
      "target": "dashboard_page_handledeletemonthlyincomeoverride",
      "confidence_score": 1.0
    },
    {
      "relation": "contains",
      "confidence": "EXTRACTED",
      "source_file": "src/app/dashboard/page.tsx",
      "source_location": "L233",
      "weight": 1.0,
      "_src": "src_app_dashboard_page_tsx",
      "_tgt": "dashboard_page_handlesetfixedexpenseoverride",
      "source": "src_app_dashboard_page_tsx",
      "target": "dashboard_page_handlesetfixedexpenseoverride",
      "confidence_score": 1.0
    },
    {
      "relation": "contains",
      "confidence": "EXTRACTED",
      "source_file": "src/app/dashboard/page.tsx",
      "source_location": "L250",
      "weight": 1.0,
      "_src": "src_app_dashboard_page_tsx",
      "_tgt": "dashboard_page_handledeletefixedexpenseoverride",
      "source": "src_app_dashboard_page_tsx",
      "target": "dashboard_page_handledeletefixedexpenseoverride",
      "confidence_score": 1.0
    },
    {
      "relation": "contains",
      "confidence": "EXTRACTED",
      "source_file": "src/app/dashboard/page.tsx",
      "source_location": "L267",
      "weight": 1.0,
      "_src": "src_app_dashboard_page_tsx",
      "_tgt": "dashboard_page_handleaddtransaction",
      "source": "src_app_dashboard_page_tsx",
      "target": "dashboard_page_handleaddtransaction",
      "confidence_score": 1.0
    },
    {
      "relation": "contains",
      "confidence": "EXTRACTED",
      "source_file": "src/app/dashboard/page.tsx",
      "source_location": "L336",
      "weight": 1.0,
      "_src": "src_app_dashboard_page_tsx",
      "_tgt": "dashboard_page_handledeletetransaction",
      "source": "src_app_dashboard_page_tsx",
      "target": "dashboard_page_handledeletetransaction",
      "confidence_score": 1.0
    },
    {
      "relation": "calls",
      "confidence": "EXTRACTED",
      "source_file": "src/app/dashboard/page.tsx",
      "source_location": "L159",
      "weight": 1.0,
      "_src": "dashboard_page_handleconfigadd",
      "_tgt": "dashboard_page_getpastmonthkeys",
      "source": "dashboard_page_getpastmonthkeys",
      "target": "dashboard_page_handleconfigadd",
      "confidence_score": 1.0
    },
    {
      "relation": "calls",
      "confidence": "EXTRACTED",
      "source_file": "src/app/dashboard/page.tsx",
      "source_location": "L174",
      "weight": 1.0,
      "_src": "dashboard_page_handleconfigedit",
      "_tgt": "dashboard_page_getpastmonthkeys",
      "source": "dashboard_page_getpastmonthkeys",
      "target": "dashboard_page_handleconfigedit",
      "confidence_score": 1.0
    },
    {
      "relation": "calls",
      "confidence": "EXTRACTED",
      "source_file": "src/app/dashboard/page.tsx",
      "source_location": "L199",
      "weight": 1.0,
      "_src": "dashboard_page_handlesetincome",
      "_tgt": "dashboard_page_getpastmonthkeys",
      "source": "dashboard_page_getpastmonthkeys",
      "target": "dashboard_page_handlesetincome",
      "confidence_score": 1.0
    },
    {
      "relation": "contains",
      "confidence": "EXTRACTED",
      "source_file": "src/app/api/transactions/route.ts",
      "source_location": "L5",
      "weight": 1.0,
      "_src": "src_app_api_transactions_route_ts",
      "_tgt": "transactions_route_get",
      "source": "src_app_api_transactions_route_ts",
      "target": "transactions_route_get",
      "confidence_score": 1.0
    },
    {
      "relation": "contains",
      "confidence": "EXTRACTED",
      "source_file": "src/app/api/transactions/delete/route.ts",
      "source_location": "L5",
      "weight": 1.0,
      "_src": "src_app_api_transactions_delete_route_ts",
      "_tgt": "delete_route_post",
      "source": "src_app_api_transactions_delete_route_ts",
      "target": "delete_route_post",
      "confidence_score": 1.0
    },
    {
      "relation": "contains",
      "confidence": "EXTRACTED",
      "source_file": "src/app/api/transactions/add/route.ts",
      "source_location": "L5",
      "weight": 1.0,
      "_src": "src_app_api_transactions_add_route_ts",
      "_tgt": "add_route_post",
      "source": "src_app_api_transactions_add_route_ts",
      "target": "add_route_post",
      "confidence_score": 1.0
    },
    {
      "relation": "contains",
      "confidence": "EXTRACTED",
      "source_file": "src/app/api/sheets/create/route.ts",
      "source_location": "L5",
      "weight": 1.0,
      "_src": "src_app_api_sheets_create_route_ts",
      "_tgt": "create_route_post",
      "source": "src_app_api_sheets_create_route_ts",
      "target": "create_route_post",
      "confidence_score": 1.0
    },
    {
      "relation": "contains",
      "confidence": "EXTRACTED",
      "source_file": "src/app/api/sheets/details/route.ts",
      "source_location": "L5",
      "weight": 1.0,
      "_src": "src_app_api_sheets_details_route_ts",
      "_tgt": "details_route_get",
      "source": "src_app_api_sheets_details_route_ts",
      "target": "details_route_get",
      "confidence_score": 1.0
    },
    {
      "relation": "contains",
      "confidence": "EXTRACTED",
      "source_file": "src/app/api/sheets/select/route.ts",
      "source_location": "L5",
      "weight": 1.0,
      "_src": "src_app_api_sheets_select_route_ts",
      "_tgt": "select_route_post",
      "source": "src_app_api_sheets_select_route_ts",
      "target": "select_route_post",
      "confidence_score": 1.0
    },
    {
      "relation": "contains",
      "confidence": "EXTRACTED",
      "source_file": "src/app/api/sheets/list/route.ts",
      "source_location": "L5",
      "weight": 1.0,
      "_src": "src_app_api_sheets_list_route_ts",
      "_tgt": "list_route_get",
      "source": "src_app_api_sheets_list_route_ts",
      "target": "list_route_get",
      "confidence_score": 1.0
    },
    {
      "relation": "contains",
      "confidence": "EXTRACTED",
      "source_file": "src/app/api/config/route.ts",
      "source_location": "L5",
      "weight": 1.0,
      "_src": "src_app_api_config_route_ts",
      "_tgt": "config_route_get",
      "source": "src_app_api_config_route_ts",
      "target": "config_route_get",
      "confidence_score": 1.0
    },
    {
      "relation": "contains",
      "confidence": "EXTRACTED",
      "source_file": "src/app/api/config/update/route.ts",
      "source_location": "L5",
      "weight": 1.0,
      "_src": "src_app_api_config_update_route_ts",
      "_tgt": "update_route_post",
      "source": "src_app_api_config_update_route_ts",
      "target": "update_route_post",
      "confidence_score": 1.0
    },
    {
      "relation": "contains",
      "confidence": "EXTRACTED",
      "source_file": "src/components/sheets/SheetSelector.tsx",
      "source_location": "L15",
      "weight": 1.0,
      "_src": "src_components_sheets_sheetselector_tsx",
      "_tgt": "sheets_sheetselector_sheetsicon",
      "source": "src_components_sheets_sheetselector_tsx",
      "target": "sheets_sheetselector_sheetsicon",
      "confidence_score": 1.0
    },
    {
      "relation": "contains",
      "confidence": "EXTRACTED",
      "source_file": "src/components/dashboard/OverviewTab.tsx",
      "source_location": "L12",
      "weight": 1.0,
      "_src": "src_components_dashboard_overviewtab_tsx",
      "_tgt": "dashboard_overviewtab_fmt",
      "source": "src_components_dashboard_overviewtab_tsx",
      "target": "dashboard_overviewtab_fmt",
      "confidence_score": 1.0
    },
    {
      "relation": "contains",
      "confidence": "EXTRACTED",
      "source_file": "src/components/dashboard/OverviewTab.tsx",
      "source_location": "L172",
      "weight": 1.0,
      "_src": "src_components_dashboard_overviewtab_tsx",
      "_tgt": "dashboard_overviewtab_handlesaveincomeoverride",
      "source": "src_components_dashboard_overviewtab_tsx",
      "target": "dashboard_overviewtab_handlesaveincomeoverride",
      "confidence_score": 1.0
    },
    {
      "relation": "contains",
      "confidence": "EXTRACTED",
      "source_file": "src/components/dashboard/OverviewTab.tsx",
      "source_location": "L188",
      "weight": 1.0,
      "_src": "src_components_dashboard_overviewtab_tsx",
      "_tgt": "dashboard_overviewtab_handlesavefixeditem",
      "source": "src_components_dashboard_overviewtab_tsx",
      "target": "dashboard_overviewtab_handlesavefixeditem",
      "confidence_score": 1.0
    },
    {
      "relation": "contains",
      "confidence": "EXTRACTED",
      "source_file": "src/components/dashboard/OverviewTab.tsx",
      "source_location": "L206",
      "weight": 1.0,
      "_src": "src_components_dashboard_overviewtab_tsx",
      "_tgt": "dashboard_overviewtab_handleresetallfixed",
      "source": "src_components_dashboard_overviewtab_tsx",
      "target": "dashboard_overviewtab_handleresetallfixed",
      "confidence_score": 1.0
    },
    {
      "relation": "contains",
      "confidence": "EXTRACTED",
      "source_file": "src/components/dashboard/OverviewTab.tsx",
      "source_location": "L227",
      "weight": 1.0,
      "_src": "src_components_dashboard_overviewtab_tsx",
      "_tgt": "dashboard_overviewtab_daylabel",
      "source": "src_components_dashboard_overviewtab_tsx",
      "target": "dashboard_overviewtab_daylabel",
      "confidence_score": 1.0
    },
    {
      "relation": "contains",
      "confidence": "EXTRACTED",
      "source_file": "/home/peter/Budget/src/components/dashboard/SettingsTab.tsx",
      "source_location": "L18",
      "weight": 1.0,
      "_src": "home_peter_budget_src_components_dashboard_settingstab_tsx",
      "_tgt": "dashboard_settingstab_pencilbtn",
      "source": "home_peter_budget_src_components_dashboard_settingstab_tsx",
      "target": "dashboard_settingstab_pencilbtn",
      "confidence_score": 1.0
    },
    {
      "relation": "contains",
      "confidence": "EXTRACTED",
      "source_file": "/home/peter/Budget/src/components/dashboard/SettingsTab.tsx",
      "source_location": "L44",
      "weight": 1.0,
      "_src": "home_peter_budget_src_components_dashboard_settingstab_tsx",
      "_tgt": "dashboard_settingstab_deletebtn",
      "source": "home_peter_budget_src_components_dashboard_settingstab_tsx",
      "target": "dashboard_settingstab_deletebtn",
      "confidence_score": 1.0
    },
    {
      "relation": "contains",
      "confidence": "EXTRACTED",
      "source_file": "/home/peter/Budget/src/components/dashboard/SettingsTab.tsx",
      "source_location": "L190",
      "weight": 1.0,
      "_src": "home_peter_budget_src_components_dashboard_settingstab_tsx",
      "_tgt": "dashboard_settingstab_handleadd",
      "source": "home_peter_budget_src_components_dashboard_settingstab_tsx",
      "target": "dashboard_settingstab_handleadd",
      "confidence_score": 1.0
    },
    {
      "relation": "contains",
      "confidence": "EXTRACTED",
      "source_file": "/home/peter/Budget/src/components/dashboard/SettingsTab.tsx",
      "source_location": "L200",
      "weight": 1.0,
      "_src": "home_peter_budget_src_components_dashboard_settingstab_tsx",
      "_tgt": "dashboard_settingstab_handledelete",
      "source": "home_peter_budget_src_components_dashboard_settingstab_tsx",
      "target": "dashboard_settingstab_handledelete",
      "confidence_score": 1.0
    },
    {
      "relation": "contains",
      "confidence": "EXTRACTED",
      "source_file": "/home/peter/Budget/src/components/dashboard/SettingsTab.tsx",
      "source_location": "L206",
      "weight": 1.0,
      "_src": "home_peter_budget_src_components_dashboard_settingstab_tsx",
      "_tgt": "dashboard_settingstab_startedit",
      "source": "home_peter_budget_src_components_dashboard_settingstab_tsx",
      "target": "dashboard_settingstab_startedit",
      "confidence_score": 1.0
    },
    {
      "relation": "contains",
      "confidence": "EXTRACTED",
      "source_file": "/home/peter/Budget/src/components/dashboard/SettingsTab.tsx",
      "source_location": "L213",
      "weight": 1.0,
      "_src": "home_peter_budget_src_components_dashboard_settingstab_tsx",
      "_tgt": "dashboard_settingstab_saveedit",
      "source": "home_peter_budget_src_components_dashboard_settingstab_tsx",
      "target": "dashboard_settingstab_saveedit",
      "confidence_score": 1.0
    },
    {
      "relation": "contains",
      "confidence": "EXTRACTED",
      "source_file": "/home/peter/Budget/src/components/dashboard/SettingsTab.tsx",
      "source_location": "L172",
      "weight": 1.0,
      "_src": "home_peter_budget_src_components_dashboard_settingstab_tsx",
      "_tgt": "dashboard_settingstab_handleamountchange",
      "source": "home_peter_budget_src_components_dashboard_settingstab_tsx",
      "target": "dashboard_settingstab_handleamountchange",
      "confidence_score": 1.0
    },
    {
      "relation": "contains",
      "confidence": "EXTRACTED",
      "source_file": "/home/peter/Budget/src/components/dashboard/SettingsTab.tsx",
      "source_location": "L181",
      "weight": 1.0,
      "_src": "home_peter_budget_src_components_dashboard_settingstab_tsx",
      "_tgt": "dashboard_settingstab_handlepctchange",
      "source": "home_peter_budget_src_components_dashboard_settingstab_tsx",
      "target": "dashboard_settingstab_handlepctchange",
      "confidence_score": 1.0
    },
    {
      "relation": "contains",
      "confidence": "EXTRACTED",
      "source_file": "/home/peter/Budget/src/components/dashboard/SettingsTab.tsx",
      "source_location": "L391",
      "weight": 1.0,
      "_src": "home_peter_budget_src_components_dashboard_settingstab_tsx",
      "_tgt": "dashboard_settingstab_fmtamt",
      "source": "home_peter_budget_src_components_dashboard_settingstab_tsx",
      "target": "dashboard_settingstab_fmtamt",
      "confidence_score": 1.0
    },
    {
      "relation": "contains",
      "confidence": "EXTRACTED",
      "source_file": "/home/peter/Budget/src/components/dashboard/SettingsTab.tsx",
      "source_location": "L221",
      "weight": 1.0,
      "_src": "home_peter_budget_src_components_dashboard_settingstab_tsx",
      "_tgt": "dashboard_settingstab_topct",
      "source": "home_peter_budget_src_components_dashboard_settingstab_tsx",
      "target": "dashboard_settingstab_topct",
      "confidence_score": 1.0
    },
    {
      "relation": "contains",
      "confidence": "EXTRACTED",
      "source_file": "/home/peter/Budget/src/components/dashboard/SettingsTab.tsx",
      "source_location": "L418",
      "weight": 1.0,
      "_src": "home_peter_budget_src_components_dashboard_settingstab_tsx",
      "_tgt": "dashboard_settingstab_handlesaveincome",
      "source": "home_peter_budget_src_components_dashboard_settingstab_tsx",
      "target": "dashboard_settingstab_handlesaveincome",
      "confidence_score": 1.0
    },
    {
      "relation": "contains",
      "confidence": "EXTRACTED",
      "source_file": "src/components/dashboard/EverythingTab.tsx",
      "source_location": "L15",
      "weight": 1.0,
      "_src": "src_components_dashboard_everythingtab_tsx",
      "_tgt": "dashboard_everythingtab_fmt",
      "source": "src_components_dashboard_everythingtab_tsx",
      "target": "dashboard_everythingtab_fmt",
      "confidence_score": 1.0
    },
    {
      "relation": "contains",
      "confidence": "EXTRACTED",
      "source_file": "src/components/dashboard/EverythingTab.tsx",
      "source_location": "L19",
      "weight": 1.0,
      "_src": "src_components_dashboard_everythingtab_tsx",
      "_tgt": "dashboard_everythingtab_yaxisfmt",
      "source": "src_components_dashboard_everythingtab_tsx",
      "target": "dashboard_everythingtab_yaxisfmt",
      "confidence_score": 1.0
    },
    {
      "relation": "contains",
      "confidence": "EXTRACTED",
      "source_file": "src/components/dashboard/EverythingTab.tsx",
      "source_location": "L23",
      "weight": 1.0,
      "_src": "src_components_dashboard_everythingtab_tsx",
      "_tgt": "dashboard_everythingtab_keytoshortlabel",
      "source": "src_components_dashboard_everythingtab_tsx",
      "target": "dashboard_everythingtab_keytoshortlabel",
      "confidence_score": 1.0
    },
    {
      "relation": "contains",
      "confidence": "EXTRACTED",
      "source_file": "src/components/dashboard/EverythingTab.tsx",
      "source_location": "L28",
      "weight": 1.0,
      "_src": "src_components_dashboard_everythingtab_tsx",
      "_tgt": "dashboard_everythingtab_keytofulllabel",
      "source": "src_components_dashboard_everythingtab_tsx",
      "target": "dashboard_everythingtab_keytofulllabel",
      "confidence_score": 1.0
    },
    {
      "relation": "contains",
      "confidence": "EXTRACTED",
      "source_file": "src/components/dashboard/EverythingTab.tsx",
      "source_location": "L65",
      "weight": 1.0,
      "_src": "src_components_dashboard_everythingtab_tsx",
      "_tgt": "dashboard_everythingtab_handleclick",
      "source": "src_components_dashboard_everythingtab_tsx",
      "target": "dashboard_everythingtab_handleclick",
      "confidence_score": 1.0
    },
    {
      "relation": "contains",
      "confidence": "EXTRACTED",
      "source_file": "src/components/dashboard/EverythingTab.tsx",
      "source_location": "L148",
      "weight": 1.0,
      "_src": "src_components_dashboard_everythingtab_tsx",
      "_tgt": "dashboard_everythingtab_togglesort",
      "source": "src_components_dashboard_everythingtab_tsx",
      "target": "dashboard_everythingtab_togglesort",
      "confidence_score": 1.0
    },
    {
      "relation": "contains",
      "confidence": "EXTRACTED",
      "source_file": "src/components/dashboard/EverythingTab.tsx",
      "source_location": "L153",
      "weight": 1.0,
      "_src": "src_components_dashboard_everythingtab_tsx",
      "_tgt": "dashboard_everythingtab_togglemonth",
      "source": "src_components_dashboard_everythingtab_tsx",
      "target": "dashboard_everythingtab_togglemonth",
      "confidence_score": 1.0
    },
    {
      "relation": "contains",
      "confidence": "EXTRACTED",
      "source_file": "/home/peter/Budget/src/components/dashboard/TransactionsTab.tsx",
      "source_location": "L9",
      "weight": 1.0,
      "_src": "home_peter_budget_src_components_dashboard_transactionstab_tsx",
      "_tgt": "dashboard_transactionstab_fmt",
      "source": "home_peter_budget_src_components_dashboard_transactionstab_tsx",
      "target": "dashboard_transactionstab_fmt",
      "confidence_score": 1.0
    },
    {
      "relation": "contains",
      "confidence": "EXTRACTED",
      "source_file": "/home/peter/Budget/src/components/dashboard/TransactionsTab.tsx",
      "source_location": "L13",
      "weight": 1.0,
      "_src": "home_peter_budget_src_components_dashboard_transactionstab_tsx",
      "_tgt": "dashboard_transactionstab_todayiso",
      "source": "home_peter_budget_src_components_dashboard_transactionstab_tsx",
      "target": "dashboard_transactionstab_todayiso",
      "confidence_score": 1.0
    },
    {
      "relation": "contains",
      "confidence": "EXTRACTED",
      "source_file": "/home/peter/Budget/src/components/dashboard/TransactionsTab.tsx",
      "source_location": "L103",
      "weight": 1.0,
      "_src": "home_peter_budget_src_components_dashboard_transactionstab_tsx",
      "_tgt": "dashboard_transactionstab_clearfilters",
      "source": "home_peter_budget_src_components_dashboard_transactionstab_tsx",
      "target": "dashboard_transactionstab_clearfilters",
      "confidence_score": 1.0
    },
    {
      "relation": "contains",
      "confidence": "EXTRACTED",
      "source_file": "/home/peter/Budget/src/components/dashboard/TransactionsTab.tsx",
      "source_location": "L110",
      "weight": 1.0,
      "_src": "home_peter_budget_src_components_dashboard_transactionstab_tsx",
      "_tgt": "dashboard_transactionstab_prevmonth",
      "source": "home_peter_budget_src_components_dashboard_transactionstab_tsx",
      "target": "dashboard_transactionstab_prevmonth",
      "confidence_score": 1.0
    },
    {
      "relation": "contains",
      "confidence": "EXTRACTED",
      "source_file": "/home/peter/Budget/src/components/dashboard/TransactionsTab.tsx",
      "source_location": "L117",
      "weight": 1.0,
      "_src": "home_peter_budget_src_components_dashboard_transactionstab_tsx",
      "_tgt": "dashboard_transactionstab_nextmonth",
      "source": "home_peter_budget_src_components_dashboard_transactionstab_tsx",
      "target": "dashboard_transactionstab_nextmonth",
      "confidence_score": 1.0
    },
    {
      "relation": "contains",
      "confidence": "EXTRACTED",
      "source_file": "/home/peter/Budget/src/components/dashboard/TransactionsTab.tsx",
      "source_location": "L125",
      "weight": 1.0,
      "_src": "home_peter_budget_src_components_dashboard_transactionstab_tsx",
      "_tgt": "dashboard_transactionstab_handleadd",
      "source": "home_peter_budget_src_components_dashboard_transactionstab_tsx",
      "target": "dashboard_transactionstab_handleadd",
      "confidence_score": 1.0
    },
    {
      "relation": "contains",
      "confidence": "EXTRACTED",
      "source_file": "/home/peter/Budget/src/components/dashboard/TransactionsTab.tsx",
      "source_location": "L144",
      "weight": 1.0,
      "_src": "home_peter_budget_src_components_dashboard_transactionstab_tsx",
      "_tgt": "dashboard_transactionstab_handledelete",
      "source": "home_peter_budget_src_components_dashboard_transactionstab_tsx",
      "target": "dashboard_transactionstab_handledelete",
      "confidence_score": 1.0
    },
    {
      "relation": "contains",
      "confidence": "EXTRACTED",
      "source_file": "/home/peter/Budget/src/components/dashboard/TransactionsTab.tsx",
      "source_location": "L165",
      "weight": 1.0,
      "_src": "home_peter_budget_src_components_dashboard_transactionstab_tsx",
      "_tgt": "dashboard_transactionstab_ondown",
      "source": "home_peter_budget_src_components_dashboard_transactionstab_tsx",
      "target": "dashboard_transactionstab_ondown",
      "confidence_score": 1.0
    },
    {
      "relation": "calls",
      "confidence": "EXTRACTED",
      "source_file": "/home/peter/Budget/src/components/dashboard/TransactionsTab.tsx",
      "source_location": "L135",
      "weight": 1.0,
      "_src": "dashboard_transactionstab_handleadd",
      "_tgt": "dashboard_transactionstab_todayiso",
      "source": "dashboard_transactionstab_todayiso",
      "target": "dashboard_transactionstab_handleadd",
      "confidence_score": 1.0
    }
  ],
  "hyperedges": []
}